topsis_Shaurya_102103625/102103625.py
topsis_Shaurya_102103625/__init__.py
topsis_Shaurya_102103625-0.1.dist-info/Licence.txt
topsis_Shaurya_102103625-0.1.dist-info/METADATA
topsis_Shaurya_102103625-0.1.dist-info/WHEEL
topsis_Shaurya_102103625-0.1.dist-info/top_level.txt
topsis_Shaurya_102103625-0.1.dist-info/RECORD
