Metadata-Version: 2.1
Name: topsis-Shaurya-102103625
Version: 0.1
Summary: Assignment_Shaurya
License-File: Licence.txt
